Codes/memory.v
`timescale 1ns/10ps

module dataMem(clk, Add, wEn, M_valA, rEn, m_valM, dmem_err);

    input clk, wEn, rEn;
    input [63:0] Add;
    input [63:0] M_valA;

    output reg [63:0] m_valM;
    output reg dmem_err;

    initial begin
        dmem_err = 0;
    end

    reg [63:0] memory [0:1023];

    always @(*) begin
        if (!(wEn & rEn) && ((0 <= Add) && (Add < 1024)) ) begin
            if (wEn & !rEn) begin
                memory[Add] = M_valA;
                dmem_err = 0;
            end

            if (rEn & !wEn) begin
                m_valM = memory[Add];
                dmem_err = 0;
            end

            if (!rEn & !wEn) begin
                dmem_err = 1;
                m_valM = 8'hx;
            end

        end   

        else
        begin
          dmem_err = 1;
          m_valM = 8'hx; // settting the value to unknown ( cause data is not read )
        end  
    
    end

endmodule

Codes/memory_tb.v

`timescale 1ns/1ps

module testbench;

    reg [63:0] Add;
    reg [63:0] M_valA;  // value to be written 
    reg clk;
    reg wEn, rEn;
    reg test;

    wire [63:0] m_valM;  // value to be read 
    wire dmem_err;

    initial
    begin
        $dumpfile("Memory_dump.vcd");
        $dumpvars(0, testbench);
        
        clk = 1'b0;
    end

    initial begin
        repeat (10) begin
        clk = 0;
        #5;
        clk = ~clk;
        #5;
        end
    end

    dataMem M1 (clk, Add, wEn, M_valA, rEn, m_valM, dmem_err);

    initial begin

       

        wEn = 1'b1;
        rEn = 1'b0;
        Add = 64'd101;
        M_valA = 64'd3025;
        #10

        if(dmem_err==1) begin
            $display("Memory Error detected");
        end

        $display("Write = %b", wEn);
        $display("Read = %b", rEn);
        $display("Address = %3d" , Add);
        $display("Input = %3d", M_valA);
        $display("Output (Memory value) = %3d\n\n" , m_valM);

        
        wEn = 1'b0;
        rEn = 1'b0;
        Add = 64'd201;
        M_valA = 64'd6045;
        #10



        if(dmem_err==1) begin
            $display("Memory Error detected");
        end

        $display("Write = %b", wEn);
        $display("Read = %b", rEn);
        $display("Address = %3d" , Add);
        $display("Input = %3d", M_valA);
        $display("Output (Memory value) = %3d\n\n" , m_valM);


    
        wEn = 1'b0;
        rEn = 1'b1;
        Add = 64'd101;
        M_valA = 64'd4025;
        #10



        if(dmem_err==1) begin

            $display("Memory Error detected");

        end
        $display("Write = %b", wEn);
        $display("Read = %b", rEn);
        $display("Address = %3d" , Add);
        $display("Input = %3d", M_valA);
        $display("Output (Memory value) = %3d\n\n" , m_valM);
        

        wEn = 1'b0;
        rEn = 1'b1;
        Add = 64'd201;
        M_valA = 64'd6045;
        #10


        if(dmem_err==1) begin
            $display("Memory Error detected");

        end

        $display("Write = %b", wEn);
        $display("Read = %b", rEn);
        $display("Address = %3d" , Add);
        $display("Input = %3d", M_valA);
        $display("Output (Memory value) = %3d\n\n" , m_valM);

        wEn = 1'b1;
        rEn = 1'b0;
        Add = 64'd401;
        M_valA = 64'd4576;
        #10

        if(dmem_err==1) begin
            $display("Memory Error detected");
        end

        $display("Write = %b", wEn);
        $display("Read = %b", rEn);
        $display("Address = %3d" , Add);
        $display("Input = %3d", M_valA);
        $display("Output (Memory value) = %3d\n\n" , m_valM);

        wEn = 1'b0;
        rEn = 1'b1;
        Add = 64'd401;
        M_valA = 64'd6045;
        #10

        if(dmem_err==1) begin
            $display("Memory Error detected");

        end

        $display("Write = %b", wEn);
        $display("Read = %b", rEn);
        $display("Address = %3d" , Add);
        $display("Input = %3d", M_valA);
        $display("Output (Memory value) = %3d\n\n" , m_valM);


        wEn = 1'b1;
        rEn = 1'b1;
        Add = 64'd401;
        M_valA = 64'd6045;
        #10


        if(dmem_err==1) begin
            $display("Memory Error detected");
        end

        $display("Write = %b", wEn);
        $display("Read = %b", rEn);
        $display("Address = %3d" , Add);
        $display("Input = %3d", M_valA);
        $display("Output (Memory value) = %3d\n\n" , m_valM);


        // more than 1024 address location 

        wEn = 1'b0;
        rEn = 1'b1;
        Add = 64'd2905;
        M_valA = 64'd6045;
        test = $bits(Add);
        #10


        if(dmem_err==1) begin
            $display("Memory Error detected");

        end

        $display("Write = %b", wEn);
        $display("Read = %b", rEn);
        $display("Address = %3d" , Add);
        $display("Input = %3d", M_valA);
        $display("Output (Memory value) = %3d\n\n" , m_valM);


    end


endmodule

Codes/Memory_dump.vcd
$date
	Thu Jan 25 19:46:07 2024
$end
$version
	Icarus Verilog
$end
$timescale
	1ps
$end
$scope module testbench $end
$var wire 64 ! m_valM [63:0] $end
$var wire 1 " dmem_err $end
$var reg 64 # Add [63:0] $end
$var reg 64 $ M_valA [63:0] $end
$var reg 1 % clk $end
$var reg 1 & rEn $end
$var reg 1 ' test $end
$var reg 1 ( wEn $end
$scope module M1 $end
$var wire 64 ) Add [63:0] $end
$var wire 64 * M_valA [63:0] $end
$var wire 1 % clk $end
$var wire 1 & rEn $end
$var wire 1 ( wEn $end
$var reg 1 " dmem_err $end
$var reg 64 + m_valM [63:0] $end
$upscope $end
$upscope $end
$enddefinitions $end
#0
$dumpvars
bx +
b101111010001 *
b1100101 )
1(
x'
0&
0%
b101111010001 $
b1100101 #
0"
bx !
$end
#5000
1%
#10000
b0xxxxxxxx !
b0xxxxxxxx +
1"
0%
b1011110011101 $
b1011110011101 *
b11001001 #
b11001001 )
0(
#15000
1%
#20000
0"
b101111010001 !
b101111010001 +
0%
b111110111001 $
b111110111001 *
b1100101 #
b1100101 )
1&
#25000
1%
#30000
bx !
bx +
0%
b1011110011101 $
b1011110011101 *
b11001001 #
b11001001 )
#35000
1%
#40000
0%
b1000111100000 $
b1000111100000 *
b110010001 #
b110010001 )
0&
1(
#45000
1%
#50000
b1000111100000 !
b1000111100000 +
0%
b1011110011101 $
b1011110011101 *
1&
0(
#55000
1%
#60000
b0xxxxxxxx !
b0xxxxxxxx +
1"
0%
1(
#65000
1%
#70000
0%
0'
b101101011001 #
b101101011001 )
0(
